gdpr_helpers/__init__.py
gdpr_helpers/admin.py
gdpr_helpers/apps.py
gdpr_helpers/forms.py
gdpr_helpers/managers.py
gdpr_helpers/middleware.py
gdpr_helpers/models.py
gdpr_helpers/utils.py
gdpr_helpers/migrations/0001_initial.py
gdpr_helpers/migrations/0002_auto_20200305_1530.py
gdpr_helpers/migrations/0003_auto_20200414_1324.py
gdpr_helpers/migrations/0004_auto_20200717_1413.py
gdpr_helpers/migrations/0005_legalreason_name.py
gdpr_helpers/migrations/0006_add_slug_field.py
gdpr_helpers/migrations/0007_populate_slug_values.py
gdpr_helpers/migrations/0008_remove_slug_null.py
gdpr_helpers/migrations/0009_auto_20211116_1131.py
gdpr_helpers/migrations/__init__.py
sandbox/__init__.py
sandbox/manage.py
sandbox/settings.py
sandbox/urls.py
sandbox/example_app/__init__.py
sandbox/example_app/admin.py
sandbox/example_app/apps.py
sandbox/example_app/forms.py
sandbox/example_app/models.py
sandbox/example_app/urls.py
sandbox/example_app/views.py
sandbox/example_app/migrations/0001_initial.py
sandbox/example_app/migrations/__init__.py
django_gdpr_helpers-0.5.0.dist-info/LICENSE
django_gdpr_helpers-0.5.0.dist-info/METADATA
django_gdpr_helpers-0.5.0.dist-info/WHEEL
django_gdpr_helpers-0.5.0.dist-info/top_level.txt
django_gdpr_helpers-0.5.0.dist-info/RECORD
